maestro_python_client/CachedClient.py
maestro_python_client/Client.py
maestro_python_client/__init__.py
maestro_python_client/test_CachedClient.py
maestro_python_client/Cache/Cache.py
maestro_python_client/Cache/RedisCache.py
maestro_python_client/Cache/__init__.py
maestro_python_client/Cache/test_RedisCache.py
maestro_python_client-0.9.6.data/scripts/maestro_client
maestro_python_client-0.9.6.dist-info/METADATA
maestro_python_client-0.9.6.dist-info/WHEEL
maestro_python_client-0.9.6.dist-info/top_level.txt
maestro_python_client-0.9.6.dist-info/RECORD
